dirk/__init__.py
dirk/cli.py
dirk/files.py
dirk/init.py
dirk/settings.py
dirk/utils.py
py_dirk-0.0.6.dist-info/LICENSE
py_dirk-0.0.6.dist-info/METADATA
py_dirk-0.0.6.dist-info/WHEEL
py_dirk-0.0.6.dist-info/entry_points.txt
py_dirk-0.0.6.dist-info/top_level.txt
py_dirk-0.0.6.dist-info/RECORD
