Metadata-Version: 2.1
Name: py-dirk
Version: 0.0.6
Summary: dirk exports KUBECONFIG via direnv
Home-page: https://github.com/grothesk/py-dirk
Author: Malte Groth
Author-email: malte.groth@gmx.net
License: UNKNOWN
Keywords: cli,kubernetes,direnv
Platform: UNKNOWN
Classifier: Development Status :: 3 - Alpha
Classifier: Intended Audience :: Developers
Classifier: License :: OSI Approved :: MIT License
Classifier: Programming Language :: Python :: 3
Requires-Python: >=3.6, <4
Requires-Dist: click
